networkvi/__init__.py
networkvi/_constants.py
networkvi/_settings.py
networkvi/_types.py
networkvi/data/__init__.py
networkvi/data/_anntorchdataset.py
networkvi/data/_compat.py
networkvi/data/_constants.py
networkvi/data/_download.py
networkvi/data/_manager.py
networkvi/data/_preprocessing.py
networkvi/data/_read.py
networkvi/data/_utils.py
networkvi/data/fields/__init__.py
networkvi/data/fields/_arraylike_field.py
networkvi/data/fields/_base_field.py
networkvi/data/fields/_dataframe_field.py
networkvi/data/fields/_layer_field.py
networkvi/data/fields/_mudata.py
networkvi/data/fields/_protein.py
networkvi/data/fields/_scanvi.py
networkvi/data/fields/_uns_field.py
networkvi/dataloaders/__init__.py
networkvi/dataloaders/_ann_dataloader.py
networkvi/dataloaders/_data_splitting.py
networkvi/dataloaders/_samplers.py
networkvi/distributions/__init__.py
networkvi/distributions/_beta_binomial.py
networkvi/distributions/_constraints.py
networkvi/distributions/_negative_binomial.py
networkvi/distributions/_utils.py
networkvi/model/__init__.py
networkvi/model/_networkvi.py
networkvi/model/_utils.py
networkvi/model/base/__init__.py
networkvi/model/base/_archesmixin_networkvi.py
networkvi/model/base/_base_model.py
networkvi/model/base/_constants.py
networkvi/model/base/_de_core.py
networkvi/model/base/_differential.py
networkvi/model/base/_log_likelihood.py
networkvi/model/base/_save_load.py
networkvi/model/base/_training_mixin.py
networkvi/model/base/_vaemixin.py
networkvi/module/__init__.py
networkvi/module/_classifier.py
networkvi/module/_constants.py
networkvi/module/_networkvae.py
networkvi/module/_peakvae.py
networkvi/module/_utils.py
networkvi/module/base/__init__.py
networkvi/module/base/_base_module.py
networkvi/module/base/_decorators.py
networkvi/module/base/_embedding_mixin.py
networkvi/module/base/_pyro.py
networkvi/nn/__init__.py
networkvi/nn/_base_components.py
networkvi/nn/_block_sparse_linear.py
networkvi/nn/_embedding.py
networkvi/nn/_evaluate_funcs.py
networkvi-0.1.0.dist-info/METADATA
networkvi-0.1.0.dist-info/WHEEL
networkvi-0.1.0.dist-info/RECORD
