Metadata-Version: 2.4
Name: networkvi
Version: 0.1.0
Summary: Biologically Guided Variational Inference for Interpretable Multimodal Single-Cell Integration and Mechanistic Discovery
Project-URL: Documentation, https://networkvi.readthedocs.io
Project-URL: Source, https://github.com/LArnoldt/networkvi
Project-URL: Home-page, https://networkvi.readthedocs.io
Author: Lucas Arnoldt, Julius Upmeier zu Belzen, Luis Herrmann, Khue Nguyen, Fabian Theis, Bejamin Wild, Roland Eils
Maintainer-email: Lucas Arnoldt <lucas.arnoldt@helmholtz-munich.de>
License-Expression: BSD-3-Clause
Classifier: Development Status :: 4 - Beta
Classifier: Intended Audience :: Science/Research
Classifier: Natural Language :: English
Classifier: Operating System :: MacOS :: MacOS X
Classifier: Operating System :: Microsoft :: Windows
Classifier: Operating System :: POSIX :: Linux
Classifier: Programming Language :: Python :: 3.9
Classifier: Programming Language :: Python :: 3.10
Classifier: Programming Language :: Python :: 3.11
Classifier: Topic :: Scientific/Engineering :: Bio-Informatics
Requires-Python: <3.12,>=3.9
Requires-Dist: addict
Requires-Dist: docrep>=0.3.2
Requires-Dist: flax
Requires-Dist: goatools
Requires-Dist: lightning>=2.0
Requires-Dist: ml-collections>=0.1.1
Requires-Dist: mudata>=0.1.2
Requires-Dist: muon
Requires-Dist: numpyro>=0.12.1
Requires-Dist: pqdm
Requires-Dist: prettytable
Requires-Dist: pyro-ppl>=1.6.0
Requires-Dist: rich>=12.0.0
Requires-Dist: scikit-learn>=0.21.2
Requires-Dist: sparse>=0.14.0
Requires-Dist: tabulate
Requires-Dist: tensorboard>=2.0
Requires-Dist: torch==2.2.0
Requires-Dist: torchmetrics>=0.11.0
Requires-Dist: xarray>=2023.2.0
Provides-Extra: all
Requires-Dist: docutils!=0.18.*,!=0.19.*,>=0.8; extra == 'all'
Requires-Dist: gdown; extra == 'all'
Requires-Dist: ipython; extra == 'all'
Requires-Dist: jupyter; extra == 'all'
Requires-Dist: myst-nb; extra == 'all'
Requires-Dist: myst-parser; extra == 'all'
Requires-Dist: nbsphinx; extra == 'all'
Requires-Dist: sphinx-autodoc-typehints; extra == 'all'
Requires-Dist: sphinx-book-theme>=1.0.1; extra == 'all'
Requires-Dist: sphinx-copybutton; extra == 'all'
Requires-Dist: sphinx-design; extra == 'all'
Requires-Dist: sphinx-hoverxref; extra == 'all'
Requires-Dist: sphinx>=4.1; extra == 'all'
Requires-Dist: sphinxcontrib-bibtex>=1.0.0; extra == 'all'
Requires-Dist: sphinxext-opengraph; extra == 'all'
Provides-Extra: aws
Requires-Dist: boto3; extra == 'aws'
Provides-Extra: census
Requires-Dist: cellxgene-census; extra == 'census'
Provides-Extra: docs
Requires-Dist: docutils!=0.18.*,!=0.19.*,>=0.8; extra == 'docs'
Requires-Dist: ipython; extra == 'docs'
Requires-Dist: myst-nb; extra == 'docs'
Requires-Dist: myst-parser; extra == 'docs'
Requires-Dist: nbsphinx; extra == 'docs'
Requires-Dist: sphinx-autodoc-typehints; extra == 'docs'
Requires-Dist: sphinx-book-theme>=1.0.1; extra == 'docs'
Requires-Dist: sphinx-copybutton; extra == 'docs'
Requires-Dist: sphinx-design; extra == 'docs'
Requires-Dist: sphinx-hoverxref; extra == 'docs'
Requires-Dist: sphinx>=4.1; extra == 'docs'
Requires-Dist: sphinxcontrib-bibtex>=1.0.0; extra == 'docs'
Requires-Dist: sphinxext-opengraph; extra == 'docs'
Provides-Extra: docsbuild
Requires-Dist: docutils!=0.18.*,!=0.19.*,>=0.8; extra == 'docsbuild'
Requires-Dist: ipython; extra == 'docsbuild'
Requires-Dist: myst-nb; extra == 'docsbuild'
Requires-Dist: myst-parser; extra == 'docsbuild'
Requires-Dist: nbsphinx; extra == 'docsbuild'
Requires-Dist: sphinx-autodoc-typehints; extra == 'docsbuild'
Requires-Dist: sphinx-book-theme>=1.0.1; extra == 'docsbuild'
Requires-Dist: sphinx-copybutton; extra == 'docsbuild'
Requires-Dist: sphinx-design; extra == 'docsbuild'
Requires-Dist: sphinx-hoverxref; extra == 'docsbuild'
Requires-Dist: sphinx>=4.1; extra == 'docsbuild'
Requires-Dist: sphinxcontrib-bibtex>=1.0.0; extra == 'docsbuild'
Requires-Dist: sphinxext-opengraph; extra == 'docsbuild'
Provides-Extra: hub
Requires-Dist: huggingface-hub; extra == 'hub'
Provides-Extra: loompy
Requires-Dist: loompy>=3.0.6; extra == 'loompy'
Provides-Extra: pymde
Requires-Dist: pymde; extra == 'pymde'
Provides-Extra: regseq
Requires-Dist: biopython>=1.81; extra == 'regseq'
Requires-Dist: genomepy; extra == 'regseq'
Provides-Extra: scanpy
Requires-Dist: scanpy>=1.6; extra == 'scanpy'
Provides-Extra: tutorials
Requires-Dist: gdown; extra == 'tutorials'
Requires-Dist: jupyter; extra == 'tutorials'
